mfcs/__init__.py
mfcs/agent_prompt.py
mfcs/function_prompt.py
mfcs/memory_prompt.py
mfcs/response_parser.py
mfcs/result_manager.py
mfcs-0.1.13.dist-info/METADATA
mfcs-0.1.13.dist-info/WHEEL
mfcs-0.1.13.dist-info/licenses/LICENSE
mfcs-0.1.13.dist-info/RECORD
