Metadata-Version: 2.4
Name: mfcs
Version: 0.1.13
Summary: A Python library for function calling in LLMs
Project-URL: Homepage, https://github.com/mfcsorg/mfcs-python
Project-URL: Bug Tracker, https://github.com/mfcsorg/mfcs-python/issues
Author-email: shideqin <shisdq@gmail.com>
License-Expression: MIT
License-File: LICENSE
Keywords: ai,function-calling,llm,nlp,prompt-engineering
Classifier: Development Status :: 3 - Alpha
Classifier: Intended Audience :: Developers
Classifier: License :: OSI Approved :: MIT License
Classifier: Programming Language :: Python :: 3
Classifier: Programming Language :: Python :: 3.8
Classifier: Programming Language :: Python :: 3.9
Classifier: Programming Language :: Python :: 3.10
Classifier: Programming Language :: Python :: 3.11
Requires-Python: >=3.8
Requires-Dist: httpx>=0.24.0
Requires-Dist: openai>=1.0.0
Requires-Dist: python-dotenv>=0.19.0
